editabletuple.py
editabletuple-1.5.3.dist-info/LICENSE
editabletuple-1.5.3.dist-info/METADATA
editabletuple-1.5.3.dist-info/WHEEL
editabletuple-1.5.3.dist-info/top_level.txt
editabletuple-1.5.3.dist-info/RECORD
