Metadata-Version: 2.1
Name: editabletuple
Version: 1.5.3
Summary: Provides the editabletuple function for creating classes with a fixed sequence of fields, similar to a namedtuple, except editable
Home-page: https://github.com/mark-summerfield/editabletuple
Author: Mark Summerfield
Author-email: mark@qtrac.eu
License: GPLv3
Platform: UNKNOWN
Classifier: Development Status :: 5 - Production/Stable
Classifier: Intended Audience :: Developers
Classifier: License :: OSI Approved :: GNU General Public License v3 (GPLv3)
Classifier: Programming Language :: Python :: 3
Classifier: Programming Language :: Python :: 3.8
Classifier: Topic :: Software Development :: Libraries
Requires-Python: >=3.8
